{
  "id": "prod-env",
  "name": "Production",
  "values": [
    {
      "key": "baseUrl",
      "value": "https://api.yourdomain.com",
      "enabled": true
    },
    {
      "key": "jwt_token",
      "value": "",
      "enabled": true
    },
    {
      "key": "access_token",
      "value": "",
      "enabled": true
    },
    {
      "key": "paypal_baseUrl",
      "value": "https://api-m.paypal.com",
      "enabled": true
    },
    {
      "key": "client_credentials",
      "value": "{{PAYPAL_BASIC_CREDENTIALS}}",
      "enabled": true
    }
  ],
  "_postman_variable_scope": "environment",
  "_postman_exported_at": "2025-10-01T00:00:00Z",
  "_postman_exported_using": "Postman"
}

